MANIFEST.in
README.md
setup.py
MOM_Sanitizer.egg-info/PKG-INFO
MOM_Sanitizer.egg-info/SOURCES.txt
MOM_Sanitizer.egg-info/dependency_links.txt
MOM_Sanitizer.egg-info/requires.txt
MOM_Sanitizer.egg-info/top_level.txt
bin/sanitize
mom_sanitizer/__init__.py
mom_sanitizer/main.py
mom_sanitizer/sanitizer.py