Metadata-Version: 1.1
Name: MOM-Sanitizer
Version: 1.0.0.dev1
Summary: A regex solution to simplify searching for specific
Home-page: https://github.com/nahum-smith/mom-sanitizer
Author: ['Nahum Smith', 'Shan Grant']
Author-email: ['nahumsmith(REMOVEME)(AT)gmail(DOT)com', 'grantpka(REMOVEME)(AT)gmail(DOT)com']
License: UNKNOWN
Platform: UNKNOWN
Classifier: Operating System :: POSIX :: Linux
Classifier: Programming Language :: Python :: 3.6
Classifier: Programming Language :: Python :: 3 :: Only
Classifier: Intended Audience :: Information Technology
Classifier: Intended Audience :: System Administrators
Classifier: Topic :: Security
